Metadata-Version: 2.1
Name: odoo8-addon-delivery-carrier-deposit
Version: 8.0.0.2.2
Summary: Create deposit slips
Home-page: http://www.akretion.com/
Author: Akretion,Odoo Community Association (OCA)
Author-email: support@odoo-community.org
License: AGPL-3
Platform: UNKNOWN
Classifier: Programming Language :: Python
Classifier: Framework :: Odoo
Classifier: Framework :: Odoo :: 8.0
Classifier: License :: OSI Approved :: GNU Affero General Public License v3
Requires-Python: ~=2.7
Requires-Dist: odoo8-addon-base-delivery-carrier-label
Requires-Dist: odoo (<9.0a,>=8.0a)
